database_manager/__init__.py
database_manager/leaderboard.py
database_manager/manager.py
pp_database_manager-2.6.1.dist-info/METADATA
pp_database_manager-2.6.1.dist-info/WHEEL
pp_database_manager-2.6.1.dist-info/top_level.txt
pp_database_manager-2.6.1.dist-info/RECORD
