Metadata-Version: 2.1
Name: pp_database_manager
Version: 2.6.1
Summary: A database manager for Supabase and PocketBase
Author: Asman
Classifier: Programming Language :: Python :: 3
Classifier: License :: OSI Approved :: MIT License
Classifier: Operating System :: OS Independent
Requires-Python: >=3.10
Requires-Dist: pocketbase==0.14.0
Requires-Dist: supabase==2.7.4
Requires-Dist: python-dotenv
